Workbook

Sheet Agency-Led Growth
A1: MOTION A: AGENCY-LED GROWTH MODEL
A2: Insight 360 Go-to-Market — Month-by-Month Projections (Year 1)
A4: ASSUMPTIONS
A5: Agency base price (monthly) | B5: 499
A6: Avg integration add-ons per agency | B6: 200
A7: Avg clients per agency (ramping)
A8: Avg revenue per client (monthly) | B8: 3000
A9: Agency churn rate (monthly) | B9: 0.02
A10: New agencies per month (soft launch M1-2) | B10: 5
A11: New agencies per month (post-launch M3-6) | B11: 8
A12: New agencies per month (scale M7-12) | B12: 12
A13: Certification revenue per new agency | B13: 1500
A14: Implementation revenue per new agency | B14: 8000
A16: MONTHLY PROJECTIONS
A17: Metric | B17: Month 1 | C17: Month 2 | D17: Month 3 | E17: Month 4 | F17: Month 5 | G17: Month 6 | H17: Month 7 | I17: Month 8 | J17: Month 9 | K17: Month 10 | L17: Month 11 | M17: Month 12 | N17: TOTAL Y1
A18: New Agencies Signed | B18: 5 | C18: 5 | D18: 8 | E18: 8 | F18: 8 | G18: 8 | H18: 12 | I18: 12 | J18: 12 | K18: 12 | L18: 12 | M18: 12 | N18: =SUM(B18:M18)
A19: Cumulative Agencies (net churn) | B19: =B18 | C19: =ROUND(B19*(1-$B$9)+C18,0) | D19: =ROUND(C19*(1-$B$9)+D18,0) | E19: =ROUND(D19*(1-$B$9)+E18,0) | F19: =ROUND(E19*(1-$B$9)+F18,0) | G19: =ROUND(F19*(1-$B$9)+G18,0) | H19: =ROUND(G19*(1-$B$9)+H18,0) | I19: =ROUND(H19*(1-$B$9)+I18,0) | J19: =ROUND(I19*(1-$B$9)+J18,0) | ... M19: =ROUND(L19*(1-$B$9)+M18,0) | N19: =M19
A20: Platform MRR (agencies) | B20: =B19*$B$5 | C20: =C19*$B$5 | D20: =D19*$B$5 | E20: =E19*$B$5 | F20: =F19*$B$5 | G20: =G19*$B$5 | H20: =H19*$B$5 | I20: =I19*$B$5 | ... M20: =M19*$B$5 | N20: =SUM(B20:M20)
A21: Integration Add-On MRR | B21: =B19*$B$6 | C21: =C19*$B$6 | D21: =D19*$B$6 | E21: =E19*$B$6 | F21: =F19*$B$6 | G21: =G19*$B$6 | H21: =H19*$B$6 | I21: =I19*$B$6 | ... M21: =M19*$B$6 | N21: =SUM(B21:M21)
A22: Total Platform MRR | B22: =B20+B21 | C22: =C20+C21 | D22: =D20+D21 | E22: =E20+E21 | F22: =F20+F21 | G22: =G20+G21 | H22: =H20+H21 | I22: =I20+I21 | ... M22: =M20+M21 | N22: =SUM(B22:M22)
A24: Avg Clients per Agency (ramping) | B24: 3 | C24: 5 | D24: 7 | E24: 9 | F24: 11 | G24: 13 | H24: 15 | I24: 16 | J24: 17 | K24: 18 | L24: 19 | M24: 20
A25: Total Client Engagements | B25: =B19*B24 | C25: =C19*C24 | D25: =D19*D24 | E25: =E19*E24 | F25: =F19*F24 | G25: =G19*G24 | H25: =H19*H24 | I25: =I19*I24 | ... M25: =M19*M24 | N25: =M25
A26: Avg Client Revenue to Agency | B26: =$B$8 | C26: =$B$8 | D26: =$B$8 | E26: =$B$8 | F26: =$B$8 | G26: =$B$8 | H26: =$B$8 | I26: =$B$8 | ... M26: =$B$8
A27: Total Agency Client Revenue (ecosystem) | B27: =B25*B26 | C27: =C25*C26 | D27: =D25*D26 | E27: =E25*E26 | F27: =F25*F26 | G27: =G25*G26 | H27: =H25*H26 | I27: =I25*I26 | ... M27: =M25*M26 | N27: =SUM(B27:M27)
A29: Certification Revenue | B29: =B18*$B$13 | C29: =C18*$B$13 | D29: =D18*$B$13 | E29: =E18*$B$13 | F29: =F18*$B$13 | G29: =G18*$B$13 | H29: =H18*$B$13 | I29: =I18*$B$13 | ... M29: =M18*$B$13 | N29: =SUM(B29:M29)
A30: Implementation Revenue | B30: =B18*$B$14 | C30: =C18*$B$14 | D30: =D18*$B$14 | E30: =E18*$B$14 | F30: =F18*$B$14 | G30: =G18*$B$14 | H30: =H18*$B$14 | I30: =I18*$B$14 | ... M30: =M18*$B$14 | N30: =SUM(B30:M30)
A31: Total Services Revenue | B31: =B29+B30 | C31: =C29+C30 | D31: =D29+D30 | E31: =E29+E30 | F31: =F29+F30 | G31: =G29+G30 | H31: =H29+H30 | I31: =I29+I30 | ... M31: =M29+M30 | N31: =SUM(B31:M31)
A33: i360 Recurring Revenue (MRR) | B33: =B22 | C33: =C22 | D33: =D22 | E33: =E22 | F33: =F22 | G33: =G22 | H33: =H22 | I33: =I22 | ... M33: =M22 | N33: =SUM(B33:M33)
A34: i360 Services Revenue | B34: =B31 | C34: =C31 | D34: =D31 | E34: =E31 | F34: =F31 | G34: =G31 | H34: =H31 | I34: =I31 | ... M34: =M31 | N34: =SUM(B34:M34)
A35: i360 Total Monthly Revenue | B35: =B33+B34 | C35: =C33+C34 | D35: =D33+D34 | E35: =E33+E34 | F35: =F33+F34 | G35: =G33+G34 | H35: =H33+H34 | I35: =I33+I34 | ... M35: =M33+M34 | N35: =SUM(B35:M35)
A36: i360 Cumulative Revenue | B36: =B35 | C36: =B36+C35 | D36: =C36+D35 | E36: =D36+E35 | F36: =E36+F35 | G36: =F36+G35 | H36: =G36+H35 | I36: =H36+I35 | J36: =I36+J35 | ... M36: =L36+M35 | N36: =M36

Sheet Content-Led Growth
A1: MOTION B: CONTENT-LED GROWTH MODEL
A2: Self-Serve Starter + Business Tier Acquisition (Year 1)
A4: ASSUMPTIONS
A5: Starter monthly price | B5: 299
A6: Business monthly price | B6: 999
A7: Monthly website visitors (starting) | B7: 2000
A8: Visitor growth rate (monthly) | B8: 0.15
A9: Trial conversion rate (visitor→trial) | B9: 0.04
A10: Trial→Starter conversion | B10: 0.25
A11: Starter→Business upgrade rate (monthly) | B11: 0.08
A12: Starter churn (monthly) | B12: 0.05
A13: Business churn (monthly) | B13: 0.03
A14: Content marketing spend (monthly) | B14: 5000
A15: Paid acquisition spend (monthly, from M3) | B15: 3000
A17: MONTHLY PROJECTIONS
A18: Metric | B18: Month 1 | C18: Month 2 | D18: Month 3 | E18: Month 4 | F18: Month 5 | G18: Month 6 | H18: Month 7 | I18: Month 8 | J18: Month 9 | K18: Month 10 | L18: Month 11 | M18: Month 12 | N18: TOTAL Y1
A19: Website Visitors | B19: =$B$7 | C19: =ROUND(B19*(1+$B$8),0) | D19: =ROUND(C19*(1+$B$8),0) | E19: =ROUND(D19*(1+$B$8),0) | F19: =ROUND(E19*(1+$B$8),0) | G19: =ROUND(F19*(1+$B$8),0) | H19: =ROUND(G19*(1+$B$8),0) | I19: =ROUND(H19*(1+$B$8),0) | J19: =ROUND(I19*(1+$B$8),0) | ... M19: =ROUND(L19*(1+$B$8),0) | N19: =SUM(B19:M19)
A20: New Trials | B20: =ROUND(B19*$B$9,0) | C20: =ROUND(C19*$B$9,0) | D20: =ROUND(D19*$B$9,0) | E20: =ROUND(E19*$B$9,0) | F20: =ROUND(F19*$B$9,0) | G20: =ROUND(G19*$B$9,0) | H20: =ROUND(H19*$B$9,0) | I20: =ROUND(I19*$B$9,0) | ... M20: =ROUND(M19*$B$9,0) | N20: =SUM(B20:M20)
A21: New Starter Customers | B21: =ROUND(B20*$B$10,0) | C21: =ROUND(C20*$B$10,0) | D21: =ROUND(D20*$B$10,0) | E21: =ROUND(E20*$B$10,0) | F21: =ROUND(F20*$B$10,0) | G21: =ROUND(G20*$B$10,0) | H21: =ROUND(H20*$B$10,0) | I21: =ROUND(I20*$B$10,0) | ... M21: =ROUND(M20*$B$10,0) | N21: =SUM(B21:M21)
A22: Starter→Business Upgrades | B22: 0 | C22: =ROUND(B24*$B$11,0) | D22: =ROUND(C24*$B$11,0) | E22: =ROUND(D24*$B$11,0) | F22: =ROUND(E24*$B$11,0) | G22: =ROUND(F24*$B$11,0) | H22: =ROUND(G24*$B$11,0) | I22: =ROUND(H24*$B$11,0) | J22: =ROUND(I24*$B$11,0) | ... M22: =ROUND(L24*$B$11,0) | N22: =SUM(B22:M22)
A24: Cumulative Starter (net churn & upgrades) | B24: =B21 | C24: =MAX(ROUND(B24*(1-$B$12)-C22+C21,0),0) | D24: =MAX(ROUND(C24*(1-$B$12)-D22+D21,0),0) | E24: =MAX(ROUND(D24*(1-$B$12)-E22+E21,0),0) | F24: =MAX(ROUND(E24*(1-$B$12)-F22+F21,0),0) | G24: =MAX(ROUND(F24*(1-$B$12)-G22+G21,0),0) | H24: =MAX(ROUND(G24*(1-$B$12)-H22+H21,0),0) | I24: =MAX(ROUND(H24*(1-$B$12)-I22+I21,0),0) | J24: =MAX(ROUND(I24*(1-$B$12)-J22+J21,0),0) | ... M24: =MAX(ROUND(L24*(1-$B$12)-M22+M21,0),0) | N24: =M24
A25: Cumulative Business (net churn) | B25: =B22 | C25: =ROUND(B25*(1-$B$13)+C22,0) | D25: =ROUND(C25*(1-$B$13)+D22,0) | E25: =ROUND(D25*(1-$B$13)+E22,0) | F25: =ROUND(E25*(1-$B$13)+F22,0) | G25: =ROUND(F25*(1-$B$13)+G22,0) | H25: =ROUND(G25*(1-$B$13)+H22,0) | I25: =ROUND(H25*(1-$B$13)+I22,0) | J25: =ROUND(I25*(1-$B$13)+J22,0) | ... M25: =ROUND(L25*(1-$B$13)+M22,0) | N25: =M25
A26: Total Customers | B26: =B24+B25 | C26: =C24+C25 | D26: =D24+D25 | E26: =E24+E25 | F26: =F24+F25 | G26: =G24+G25 | H26: =H24+H25 | I26: =I24+I25 | ... M26: =M24+M25 | N26: =M26
A28: Starter MRR | B28: =B24*$B$5 | C28: =C24*$B$5 | D28: =D24*$B$5 | E28: =E24*$B$5 | F28: =F24*$B$5 | G28: =G24*$B$5 | H28: =H24*$B$5 | I28: =I24*$B$5 | ... M28: =M24*$B$5 | N28: =SUM(B28:M28)
A29: Business MRR | B29: =B25*$B$6 | C29: =C25*$B$6 | D29: =D25*$B$6 | E29: =E25*$B$6 | F29: =F25*$B$6 | G29: =G25*$B$6 | H29: =H25*$B$6 | I29: =I25*$B$6 | ... M29: =M25*$B$6 | N29: =SUM(B29:M29)
A30: Total MRR | B30: =B28+B29 | C30: =C28+C29 | D30: =D28+D29 | E30: =E28+E29 | F30: =F28+F29 | G30: =G28+G29 | H30: =H28+H29 | I30: =I28+I29 | ... M30: =M28+M29 | N30: =SUM(B30:M30)
A32: Marketing Spend | B32: =$B$14 | C32: =$B$14 | D32: =$B$14+$B$15 | E32: =$B$14+$B$15 | F32: =$B$14+$B$15 | G32: =$B$14+$B$15 | H32: =$B$14+$B$15 | I32: =$B$14+$B$15 | J32: =$B$14+$B$15 | K32: =$B$14+$B$15 | ... M32: =$B$14+$B$15 | N32: =SUM(B32:M32)
A33: CAC (per new customer) | B33: =IF(B21+B22>0,B32/(B21+B22),0) | C33: =IF(C21+C22>0,C32/(C21+C22),0) | D33: =IF(D21+D22>0,D32/(D21+D22),0) | E33: =IF(E21+E22>0,E32/(E21+E22),0) | F33: =IF(F21+F22>0,F32/(F21+F22),0) | G33: =IF(G21+G22>0,G32/(G21+G22),0) | H33: =IF(H21+H22>0,H32/(H21+H22),0) | I33: =IF(I21+I22>0,I32/(I21+I22),0) | ... N33: =IF(N21+N22>0,N32/(N21+N22),0)
A34: MRR - Marketing Spend | B34: =B30-B32 | C34: =C30-C32 | D34: =D30-D32 | E34: =E30-E32 | F34: =F30-F32 | G34: =G30-G32 | H34: =H30-H32 | I34: =I30-I32 | ... M34: =M30-M32 | N34: =SUM(B34:M34)
A35: Cumulative Revenue | B35: =B30 | C35: =B35+C30 | D35: =C35+D30 | E35: =D35+E30 | F35: =E35+F30 | G35: =F35+G30 | H35: =G35+H30 | I35: =H35+I30 | J35: =I35+J30 | ... M35: =L35+M30 | N35: =M35
A36: Cumulative Marketing Spend | B36: =B32 | C36: =B36+C32 | D36: =C36+D32 | E36: =D36+E32 | F36: =E36+F32 | G36: =F36+G32 | H36: =G36+H32 | I36: =H36+I32 | J36: =I36+J32 | ... M36: =L36+M32 | N36: =M36

Sheet Partner-Enabled Enterprise
A1: MOTION C: PARTNER-ENABLED ENTERPRISE GROWTH MODEL
A2: Partner Channel + Enterprise Direct (Year 1)
A4: ASSUMPTIONS
A5: Enterprise avg monthly deal value | B5: 3500
A6: Partner-sourced avg monthly deal value | B6: 1667
A7: New partners signed per month (M1-3) | B7: 3
A8: New partners signed per month (M4-12) | B8: 5
A9: Deals per active partner per quarter | B9: 1
A10: Enterprise direct deals per month (M4+) | B10: 1
A11: Partner margin (% of deal) | B11: 0.28
A12: i360 net revenue (% of partner deal) | B12: 0.72
A13: Enterprise churn (monthly) | B13: 0.015
A14: Partner churn (monthly) | B14: 0.04
A15: Partner enablement cost per partner | B15: 2000
A16: Enterprise sales cost per deal | B16: 5000
A18: MONTHLY PROJECTIONS
A19: Metric | B19: Month 1 | C19: Month 2 | D19: Month 3 | E19: Month 4 | F19: Month 5 | G19: Month 6 | H19: Month 7 | I19: Month 8 | J19: Month 9 | K19: Month 10 | L19: Month 11 | M19: Month 12 | N19: TOTAL Y1
A20: New Partners Signed | B20: 3 | C20: 3 | D20: 3 | E20: 5 | F20: 5 | G20: 5 | H20: 5 | I20: 5 | J20: 5 | K20: 5 | L20: 5 | M20: 5 | N20: =SUM(B20:M20)
A21: Cumulative Active Partners | B21: =B20 | C21: =ROUND(B21*(1-$B$14)+C20,0) | D21: =ROUND(C21*(1-$B$14)+D20,0) | E21: =ROUND(D21*(1-$B$14)+E20,0) | F21: =ROUND(E21*(1-$B$14)+F20,0) | G21: =ROUND(F21*(1-$B$14)+G20,0) | H21: =ROUND(G21*(1-$B$14)+H20,0) | I21: =ROUND(H21*(1-$B$14)+I20,0) | J21: =ROUND(I21*(1-$B$14)+J20,0) | ... M21: =ROUND(L21*(1-$B$14)+M20,0) | N21: =M21
A22: New Partner-Sourced Deals | B22: =ROUND(B21*$B$9/3,0) | C22: =ROUND(C21*$B$9/3,0) | D22: =ROUND(D21*$B$9/3,0) | E22: =ROUND(E21*$B$9/3,0) | F22: =ROUND(F21*$B$9/3,0) | G22: =ROUND(G21*$B$9/3,0) | H22: =ROUND(H21*$B$9/3,0) | I22: =ROUND(I21*$B$9/3,0) | ... M22: =ROUND(M21*$B$9/3,0) | N22: =SUM(B22:M22)
A23: New Enterprise Direct Deals | B23: 0 | C23: 0 | D23: 0 | E23: 1 | F23: 1 | G23: 1 | H23: 1 | I23: 2 | J23: 2 | K23: 2 | L23: 2 | M23: 2 | N23: =SUM(B23:M23)
A24: Total New Deals | B24: =B22+B23 | C24: =C22+C23 | D24: =D22+D23 | E24: =E22+E23 | F24: =F22+F23 | G24: =G22+G23 | H24: =H22+H23 | I24: =I22+I23 | ... M24: =M22+M23 | N24: =SUM(B24:M24)
A26: Cumulative Partner Customers (net churn) | B26: =B22 | C26: =ROUND(B26*(1-$B$13)+C22,0) | D26: =ROUND(C26*(1-$B$13)+D22,0) | E26: =ROUND(D26*(1-$B$13)+E22,0) | F26: =ROUND(E26*(1-$B$13)+F22,0) | G26: =ROUND(F26*(1-$B$13)+G22,0) | H26: =ROUND(G26*(1-$B$13)+H22,0) | I26: =ROUND(H26*(1-$B$13)+I22,0) | J26: =ROUND(I26*(1-$B$13)+J22,0) | ... M26: =ROUND(L26*(1-$B$13)+M22,0) | N26: =M26
A27: Cumulative Enterprise Customers (net churn) | B27: =B23 | C27: =ROUND(B27*(1-$B$13)+C23,0) | D27: =ROUND(C27*(1-$B$13)+D23,0) | E27: =ROUND(D27*(1-$B$13)+E23,0) | F27: =ROUND(E27*(1-$B$13)+F23,0) | G27: =ROUND(F27*(1-$B$13)+G23,0) | H27: =ROUND(G27*(1-$B$13)+H23,0) | I27: =ROUND(H27*(1-$B$13)+I23,0) | J27: =ROUND(I27*(1-$B$13)+J23,0) | ... M27: =ROUND(L27*(1-$B$13)+M23,0) | N27: =M27
A28: Total Active Customers | B28: =B26+B27 | C28: =C26+C27 | D28: =D26+D27 | E28: =E26+E27 | F28: =F26+F27 | G28: =G26+G27 | H28: =H26+H27 | I28: =I26+I27 | ... M28: =M26+M27 | N28: =M28
A30: Partner-Sourced MRR (i360 net) | B30: =B26*$B$6*$B$12 | C30: =C26*$B$6*$B$12 | D30: =D26*$B$6*$B$12 | E30: =E26*$B$6*$B$12 | F30: =F26*$B$6*$B$12 | G30: =G26*$B$6*$B$12 | H30: =H26*$B$6*$B$12 | I30: =I26*$B$6*$B$12 | ... M30: =M26*$B$6*$B$12 | N30: =SUM(B30:M30)
A31: Enterprise Direct MRR | B31: =B27*$B$5 | C31: =C27*$B$5 | D31: =D27*$B$5 | E31: =E27*$B$5 | F31: =F27*$B$5 | G31: =G27*$B$5 | H31: =H27*$B$5 | I31: =I27*$B$5 | ... M31: =M27*$B$5 | N31: =SUM(B31:M31)
A32: Total MRR | B32: =B30+B31 | C32: =C30+C31 | D32: =D30+D31 | E32: =E30+E31 | F32: =F30+F31 | G32: =G30+G31 | H32: =H30+H31 | I32: =I30+I31 | ... M32: =M30+M31 | N32: =SUM(B32:M32)
A34: Partner Enablement Costs | B34: =B20*$B$15 | C34: =C20*$B$15 | D34: =D20*$B$15 | E34: =E20*$B$15 | F34: =F20*$B$15 | G34: =G20*$B$15 | H34: =H20*$B$15 | I34: =I20*$B$15 | ... M34: =M20*$B$15 | N34: =SUM(B34:M34)
A35: Enterprise Sales Costs | B35: =B23*$B$16 | C35: =C23*$B$16 | D35: =D23*$B$16 | E35: =E23*$B$16 | F35: =F23*$B$16 | G35: =G23*$B$16 | H35: =H23*$B$16 | I35: =I23*$B$16 | ... M35: =M23*$B$16 | N35: =SUM(B35:M35)
A36: Total Channel Costs | B36: =B34+B35 | C36: =C34+C35 | D36: =D34+D35 | E36: =E34+E35 | F36: =F34+F35 | G36: =G34+G35 | H36: =H34+H35 | I36: =I34+I35 | ... M36: =M34+M35 | N36: =SUM(B36:M36)
A37: Net MRR (after channel costs) | B37: =B32-B36 | C37: =C32-C36 | D37: =D32-D36 | E37: =E32-E36 | F37: =F32-F36 | G37: =G32-G36 | H37: =H32-H36 | I37: =I32-I36 | ... M37: =M32-M36 | N37: =SUM(B37:M37)
A38: Cumulative Revenue | B38: =B32 | C38: =B38+C32 | D38: =C38+D32 | E38: =D38+E32 | F38: =E38+F32 | G38: =F38+G32 | H38: =G38+H32 | I38: =H38+I32 | J38: =I38+J32 | ... M38: =L38+M32 | N38: =M38

Sheet Combined Summary
A1: COMBINED GTM REVENUE SUMMARY
A2: All Three Motions — Year 1 Month-by-Month
A4: Metric | B4: Month 1 | C4: Month 2 | D4: Month 3 | E4: Month 4 | F4: Month 5 | G4: Month 6 | H4: Month 7 | I4: Month 8 | J4: Month 9 | K4: Month 10 | L4: Month 11 | M4: Month 12 | N4: TOTAL Y1
A5: Motion A: Agency MRR | B5: ='Agency-Led Growth'!B22 | C5: ='Agency-Led Growth'!C22 | D5: ='Agency-Led Growth'!D22 | E5: ='Agency-Led Growth'!E22 | F5: ='Agency-Led Growth'!F22 | G5: ='Agency-Led Growth'!G22 | H5: ='Agency-Led Growth'!H22 | I5: ='Agency-Led Growth'!I22 | ... N5: ='Agency-Led Growth'!N22
A6: Motion B: Content-Led MRR | B6: ='Content-Led Growth'!B30 | C6: ='Content-Led Growth'!C30 | D6: ='Content-Led Growth'!D30 | E6: ='Content-Led Growth'!E30 | F6: ='Content-Led Growth'!F30 | G6: ='Content-Led Growth'!G30 | H6: ='Content-Led Growth'!H30 | I6: ='Content-Led Growth'!I30 | ... N6: ='Content-Led Growth'!N30
A7: Motion C: Partner/Enterprise MRR | B7: ='Partner-Enabled Enterprise'!B32 | C7: ='Partner-Enabled Enterprise'!C32 | D7: ='Partner-Enabled Enterprise'!D32 | E7: ='Partner-Enabled Enterprise'!E32 | F7: ='Partner-Enabled Enterprise'!F32 | G7: ='Partner-Enabled Enterprise'!G32 | H7: ='Partner-Enabled Enterprise'!H32 | I7: ='Partner-Enabled Enterprise'!I32 | ... N7: ='Partner-Enabled Enterprise'!N32
A8: TOTAL MRR (all motions) | B8: =B5+B6+B7 | C8: =C5+C6+C7 | D8: =D5+D6+D7 | E8: =E5+E6+E7 | F8: =F5+F6+F7 | G8: =G5+G6+G7 | H8: =H5+H6+H7 | I8: =I5+I6+I7 | ... N8: =N5+N6+N7
A10: Motion A: Agency Services Revenue | B10: ='Agency-Led Growth'!B31 | C10: ='Agency-Led Growth'!C31 | D10: ='Agency-Led Growth'!D31 | E10: ='Agency-Led Growth'!E31 | F10: ='Agency-Led Growth'!F31 | G10: ='Agency-Led Growth'!G31 | H10: ='Agency-Led Growth'!H31 | I10: ='Agency-Led Growth'!I31 | ... N10: ='Agency-Led Growth'!N31
A11: Motion B: Marketing Spend | B11: ='Content-Led Growth'!B32 | C11: ='Content-Led Growth'!C32 | D11: ='Content-Led Growth'!D32 | E11: ='Content-Led Growth'!E32 | F11: ='Content-Led Growth'!F32 | G11: ='Content-Led Growth'!G32 | H11: ='Content-Led Growth'!H32 | I11: ='Content-Led Growth'!I32 | ... N11: ='Content-Led Growth'!N32
A12: Motion C: Channel Costs | B12: ='Partner-Enabled Enterprise'!B36 | C12: ='Partner-Enabled Enterprise'!C36 | D12: ='Partner-Enabled Enterprise'!D36 | E12: ='Partner-Enabled Enterprise'!E36 | F12: ='Partner-Enabled Enterprise'!F36 | G12: ='Partner-Enabled Enterprise'!G36 | H12: ='Partner-Enabled Enterprise'!H36 | I12: ='Partner-Enabled Enterprise'!I36 | ... N12: ='Partner-Enabled Enterprise'!N36
A14: Motion A: Cumulative Revenue | B14: ='Agency-Led Growth'!B36 | C14: ='Agency-Led Growth'!C36 | D14: ='Agency-Led Growth'!D36 | E14: ='Agency-Led Growth'!E36 | F14: ='Agency-Led Growth'!F36 | G14: ='Agency-Led Growth'!G36 | H14: ='Agency-Led Growth'!H36 | I14: ='Agency-Led Growth'!I36 | ... N14: ='Agency-Led Growth'!N36
A15: Motion B: Cumulative Revenue | B15: ='Content-Led Growth'!B35 | C15: ='Content-Led Growth'!C35 | D15: ='Content-Led Growth'!D35 | E15: ='Content-Led Growth'!E35 | F15: ='Content-Led Growth'!F35 | G15: ='Content-Led Growth'!G35 | H15: ='Content-Led Growth'!H35 | I15: ='Content-Led Growth'!I35 | ... N15: ='Content-Led Growth'!N35
A16: Motion C: Cumulative Revenue | B16: ='Partner-Enabled Enterprise'!B38 | C16: ='Partner-Enabled Enterprise'!C38 | D16: ='Partner-Enabled Enterprise'!D38 | E16: ='Partner-Enabled Enterprise'!E38 | F16: ='Partner-Enabled Enterprise'!F38 | G16: ='Partner-Enabled Enterprise'!G38 | H16: ='Partner-Enabled Enterprise'!H38 | I16: ='Partner-Enabled Enterprise'!I38 | ... N16: ='Partner-Enabled Enterprise'!N38
A17: TOTAL CUMULATIVE REVENUE | B17: =B14+B15+B16 | C17: =C14+C15+C16 | D17: =D14+D15+D16 | E17: =E14+E15+E16 | F17: =F14+F15+F16 | G17: =G14+G15+G16 | H17: =H14+H15+H16 | I17: =I14+I15+I16 | ... N17: =N14+N15+N16
A19: Motion A: Agencies (cumulative) | B19: ='Agency-Led Growth'!B19 | C19: ='Agency-Led Growth'!C19 | D19: ='Agency-Led Growth'!D19 | E19: ='Agency-Led Growth'!E19 | F19: ='Agency-Led Growth'!F19 | G19: ='Agency-Led Growth'!G19 | H19: ='Agency-Led Growth'!H19 | I19: ='Agency-Led Growth'!I19 | ... N19: ='Agency-Led Growth'!N19
A20: Motion B: Total Customers | B20: ='Content-Led Growth'!B26 | C20: ='Content-Led Growth'!C26 | D20: ='Content-Led Growth'!D26 | E20: ='Content-Led Growth'!E26 | F20: ='Content-Led Growth'!F26 | G20: ='Content-Led Growth'!G26 | H20: ='Content-Led Growth'!H26 | I20: ='Content-Led Growth'!I26 | ... N20: ='Content-Led Growth'!N26
A21: Motion C: Total Customers | B21: ='Partner-Enabled Enterprise'!B28 | C21: ='Partner-Enabled Enterprise'!C28 | D21: ='Partner-Enabled Enterprise'!D28 | E21: ='Partner-Enabled Enterprise'!E28 | F21: ='Partner-Enabled Enterprise'!F28 | G21: ='Partner-Enabled Enterprise'!G28 | H21: ='Partner-Enabled Enterprise'!H28 | I21: ='Partner-Enabled Enterprise'!I28 | ... N21: ='Partner-Enabled Enterprise'!N28
A22: TOTAL CUSTOMERS | B22: =B19+B20+B21 | C22: =C19+C20+C21 | D22: =D19+D20+D21 | E22: =E19+E20+E21 | F22: =F19+F20+F21 | G22: =G19+G20+G21 | H22: =H19+H20+H21 | I22: =I19+I20+I21 | ... N22: =N19+N20+N21
